forecast_combine/__init__.py
forecast_combine/forecast.py
forecast_combine/model_select.py
forecast_combine/reconcile.py
forecast_combine/utils/__init__.py
forecast_combine/utils/explore.py
forecast_combine/utils/metrics.py
forecast_combine/utils/plotting.py
forecast_combine-0.0.6.dist-info/LICENSE
forecast_combine-0.0.6.dist-info/METADATA
forecast_combine-0.0.6.dist-info/WHEEL
forecast_combine-0.0.6.dist-info/RECORD
