Metadata-Version: 2.1
Name: forecast_combine
Version: 0.0.6
Summary: Automation of forecast models testing, combining and predicting
Home-page: https://github.com/amineraboun/forecast
Keywords: arima,ets,theta,tbats,prophet
Author: amineraboun
Author-email: amineraboun@gmail.com
Requires-Python: >=3.9,<3.12
Classifier: License :: OSI Approved :: MIT License
Classifier: Operating System :: OS Independent
Classifier: Programming Language :: Python :: 3
Classifier: Programming Language :: Python :: 3.9
Classifier: Programming Language :: Python :: 3.10
Classifier: Programming Language :: Python :: 3.11
Requires-Dist: arch (>=6.3.0,<7.0.0)
Requires-Dist: matplotlib (>=3.7.2,<4.0.0)
Requires-Dist: openpyxl (>=3.1.2,<4.0.0)
Requires-Dist: prophet (>=1.1.4,<2.0.0)
Requires-Dist: seaborn (>=0.12.2,<0.13.0)
Requires-Dist: sktime (>=0.28.0,<0.29.0)
Requires-Dist: statsforecast (>=1.7.4,<2.0.0)
Requires-Dist: statsmodels (>=0.14.0,<0.15.0)
Requires-Dist: tbats (>=1.1.3,<2.0.0)
Requires-Dist: tqdm (>=4.66.0,<5.0.0)
Project-URL: Repository, https://github.com/amineraboun/forecast
